ml_htools
