Metadata-Version: 1.1
Name: ml-htools
Version: 1.0.1
Summary: Utilities for machine learning using scikit-learn and PyTorch.
Home-page: https://github.com/hdmamin/ml_htools
Author: Harrison Mamin
Author-email: Hmamin2@dons.usfca.edu
License: MIT license
Keywords: ml_htools
Platform: UNKNOWN
Classifier: Development Status :: 2 - Pre-Alpha
Classifier: Intended Audience :: Developers
Classifier: License :: OSI Approved :: MIT License
Classifier: Natural Language :: English
Classifier: Programming Language :: Python :: 3.6
Classifier: Programming Language :: Python :: 3.7
